README.rst
bootstrap.py
buildout.cfg
setup.cfg
setup.py
versions.cfg
docs/CREDITS.rst
docs/FUTURE.rst
docs/HISTORY.rst
docs/LICENSE.rst
docs/README.rst
docs/api.rst
docs/bacula.rst
docs/conf.py
docs/headquarters.rst
docs/hq.rst
docs/index.rst
docs/ipsec.rst
docs/projects.rst
docs/_static/placeholder
docs/etc/bacula-fd.conf.in
docs/etc/bacula-master.conf.in
docs/etc/duplicity.sh.in
docs/etc/duplicityfilelist.conf
docs/etc/nginx.conf
docs/etc/psk.txt.in
docs/etc/racoon.conf.in
niteoweb/__init__.py
niteoweb.fabfile.egg-info/PKG-INFO
niteoweb.fabfile.egg-info/SOURCES.txt
niteoweb.fabfile.egg-info/dependency_links.txt
niteoweb.fabfile.egg-info/not-zip-safe
niteoweb.fabfile.egg-info/requires.txt
niteoweb.fabfile.egg-info/top_level.txt
niteoweb/fabfile/__init__.py
niteoweb/fabfile/project.py
niteoweb/fabfile/server.py