Metadata-Version: 1.0
Name: niteoweb.fabfile
Version: 2.2
Summary: A bunch of Fabric commands we use all the time.
Home-page: http://www.niteoweb.com
Author: NiteoWeb Ltd.
Author-email: info@niteoweb.com
License: BSD
Keywords: Fabric Python
Platform: UNKNOWN
Classifier: Programming Language :: Python
